hb_test_generator/generate_tests.py
hb_test_generator-0.1.14.dist-info/METADATA
hb_test_generator-0.1.14.dist-info/WHEEL
hb_test_generator-0.1.14.dist-info/entry_points.txt
hb_test_generator-0.1.14.dist-info/top_level.txt
hb_test_generator-0.1.14.dist-info/RECORD
