Metadata-Version: 2.1
Name: hb-test-generator
Version: 0.1.14
Summary: A package to generate tests & write it into files using OpenAI's GPT-3
Home-page: https://github.com/halalbooking/hb_test_generator
Author: Maksymenkov Eugene
Author-email: foatei@gmail.com
License: UNKNOWN
Platform: UNKNOWN
Classifier: Development Status :: 3 - Alpha
Classifier: License :: OSI Approved :: MIT License
Classifier: Programming Language :: Python :: 3
Classifier: Programming Language :: Python :: 3.6
Classifier: Programming Language :: Python :: 3.7
Classifier: Programming Language :: Python :: 3.8
Classifier: Programming Language :: Python :: 3.9
Classifier: Programming Language :: Python :: 3.10
Classifier: Programming Language :: Python :: 3.11
Requires-Dist: openai
